buche/__init__.py
buche/__main__.py
buche/buche.py
buche/debug.py
buche/event.py
buche/repl.py
buche/repr.py
buche-0.2.0.dist-info/METADATA
buche-0.2.0.dist-info/RECORD
buche-0.2.0.dist-info/WHEEL
buche-0.2.0.dist-info/top_level.txt
