Metadata-Version: 2.1
Name: buche
Version: 0.2.0
Summary: Pretty-print Python objects to Buche logger.
Home-page: https://github.com/breuleux/buche
Author: Olivier Breuleux
Author-email: breuleux@gmail.com
License: MIT
Keywords: buche repr pprint html development
Platform: UNKNOWN
Classifier: Development Status :: 3 - Alpha
Classifier: Intended Audience :: Developers
Classifier: License :: OSI Approved :: MIT License
Classifier: Programming Language :: Python :: 3
Classifier: Programming Language :: Python :: 3.6
Requires-Python: >=3.6
Provides-Extra: test
Provides-Extra: dev
Requires-Dist: hrepr
Provides-Extra: dev
Provides-Extra: test
